imgui_datascience/__init__.py
imgui_datascience/__main__.py
imgui_datascience/_imgui_cv_zoom.py
imgui_datascience/example.py
imgui_datascience/imgui_cv.py
imgui_datascience/imgui_datascience.py
imgui_datascience/imgui_ext.py
imgui_datascience/imgui_fig.py
imgui_datascience/imgui_image_lister.py
imgui_datascience/imgui_runner.py
imgui_datascience/source-sans-pro.regular.ttf
imgui_datascience/static_vars.py
imgui_datascience/images/billiard.jpg
imgui_datascience/images/flower.jpg
imgui_datascience/images/owl.jpg
imgui_datascience-0.3.2.dist-info/AUTHORS.rst
imgui_datascience-0.3.2.dist-info/LICENSE
imgui_datascience-0.3.2.dist-info/METADATA
imgui_datascience-0.3.2.dist-info/WHEEL
imgui_datascience-0.3.2.dist-info/entry_points.txt
imgui_datascience-0.3.2.dist-info/top_level.txt
imgui_datascience-0.3.2.dist-info/RECORD
